arrakis_backend_kafka/__init__.py
arrakis_backend_kafka/_version.py
arrakis_backend_kafka/backend.py
arrakis_backend_kafka/tests/__init__.py
arrakis_backend_kafka/tests/test_backend.py
arrakis_backend_kafka-0.3.1.dist-info/METADATA
arrakis_backend_kafka-0.3.1.dist-info/WHEEL
arrakis_backend_kafka-0.3.1.dist-info/entry_points.txt
arrakis_backend_kafka-0.3.1.dist-info/licenses/LICENSE
arrakis_backend_kafka-0.3.1.dist-info/RECORD
